Metadata-Version: 2.1
Name: pyramid-debugtoolbar-dogpile
Version: 0.2.4
Summary: dogpile support for pyramid_debugtoolbar
Home-page: https://github.com/jvanasco/pyramid_debugtoolbar_dogpile
Author: Jonathan Vanasco
Author-email: jonathan@findmeon.com
License: MIT
Keywords: web pyramid
Platform: UNKNOWN
Classifier: Intended Audience :: Developers
Classifier: Framework :: Pyramid
Classifier: Programming Language :: Python
Classifier: Programming Language :: Python :: 2
Classifier: Programming Language :: Python :: 3
Classifier: License :: OSI Approved :: MIT License
Provides-Extra: testing
